wp_manage/VERSION
wp_manage/__init__.py
wp_manage/cli.py
wp_manage/commands.py
wp_manage/site_response.py
wp_manage/wp_manage.py
wp_manage-1.3.4.dist-info/METADATA
wp_manage-1.3.4.dist-info/WHEEL
wp_manage-1.3.4.dist-info/entry_points.txt
wp_manage-1.3.4.dist-info/RECORD
